geneweaver/tools/framework/__init__.py
geneweaver/tools/framework/abstract.py
geneweaver/tools/framework/enum.py
geneweaver/tools/framework/schema.py
geneweaver_tools-0.0.5.dist-info/LICENSE
geneweaver_tools-0.0.5.dist-info/METADATA
geneweaver_tools-0.0.5.dist-info/WHEEL
geneweaver_tools-0.0.5.dist-info/RECORD
